cumulus_fhir_support/__init__.py
cumulus_fhir_support/auth.py
cumulus_fhir_support/client.py
cumulus_fhir_support/errors.py
cumulus_fhir_support/http.py
cumulus_fhir_support/ml_json.py
cumulus_fhir_support/schemas.py
cumulus_fhir_support-1.10.0.dist-info/licenses/LICENSE
cumulus_fhir_support-1.10.0.dist-info/WHEEL
cumulus_fhir_support-1.10.0.dist-info/METADATA
cumulus_fhir_support-1.10.0.dist-info/RECORD
