Metadata-Version: 2.4
Name: cumulus-fhir-support
Version: 1.10.0
Summary: FHIR support code for the Cumulus project
Author-email: Michael Terry <michael.terry@childrens.harvard.edu>
Requires-Python: >= 3.10
License-Expression: Apache-2.0
Classifier: Operating System :: OS Independent
Classifier: Programming Language :: Python :: 3
Classifier: Topic :: Software Development :: Libraries :: Python Modules
License-File: LICENSE
Requires-Dist: fhirclient >= 4.1
Requires-Dist: httpx
Requires-Dist: jwcrypto
Requires-Dist: pyarrow >= 12
Requires-Dist: pre-commit ; extra == "dev"
Requires-Dist: ruff < 0.15 ; extra == "dev"
Requires-Dist: ddt ; extra == "tests"
Requires-Dist: fsspec ; extra == "tests"
Requires-Dist: pytest ; extra == "tests"
Requires-Dist: pytest-cov ; extra == "tests"
Requires-Dist: respx ; extra == "tests"
Requires-Dist: time-machine ; extra == "tests"
Project-URL: Homepage, https://github.com/smart-on-fhir/cumulus-fhir-support
Provides-Extra: dev
Provides-Extra: tests
